idscheck/__init__.py
idscheck/idscheck.py
idscheck-2.8.0.dist-info/LICENSE
idscheck-2.8.0.dist-info/METADATA
idscheck-2.8.0.dist-info/WHEEL
idscheck-2.8.0.dist-info/entry_points.txt
idscheck-2.8.0.dist-info/top_level.txt
idscheck-2.8.0.dist-info/RECORD
