Metadata-Version: 2.1
Name: idscheck
Version: 2.8.0
Summary: A command line tool for IDS student to check GPU allocation
Home-page: https://github.com/NaiboWang/IDSCheck
Author: Naibo Wang
Author-email: naibowang@foxmail.com
License-File: LICENSE
